OLD_SLIDES/A1/3/half_adder.v
/*************************************************
* Half Adder program
* Shanthanu S Rai(17CO242) and Varun Pattar(17CO249)
* October 13, 2018
*************************************************/

module half_adder(A,B,C,S);

input A,B;
output C,S;

and G1(C,A,B);
xor G2(S,A,B);

endmodule

OLD_SLIDES/A2-final/2/full_adder.v
/*************************************************
* Full Adder program
* Shanthanu S Rai(17CO242) and Varun Pattar(17CO249)
* October 13, 2018
*************************************************/

`include "half_adder.v"

module full_adder(A,B,Cin,Cout,S);

input A,B,Cin;
output Cout, S;
wire S1,C1,C2;

half_adder HA1(A,B,C1,S1);
half_adder HA2(S1,Cin,C2,S);
or G(Cout,C1,C2);

endmodule

OLD_SLIDES/A1/4/t_full_adder.v
/*************************************************
* Test bench for Full Adder program
* Shanthanu S Rai(17CO242) and Varun Pattar(17CO249)
* October 13, 2018
*************************************************/

`include "full_adder.v"

module t_full_adder;

reg A,B,Cin;
wire S,Cout;

full_adder FA(A,B,Cin,Cout,S);

initial begin
       $monitor($time," A = %b, B = %b, Cin = %b, Cout = %b, S = %b", A, B, Cin, Cout, S);	
	{A,B,Cin} = 3'b000;
#50	{A,B,Cin} = 3'b001;
#50	{A,B,Cin} = 3'b010;
#50	{A,B,Cin} = 3'b011;
#50	{A,B,Cin} = 3'b100;
#50	{A,B,Cin} = 3'b101;
#50	{A,B,Cin} = 3'b110;
#50	{A,B,Cin} = 3'b111;
end

initial begin
	$dumpfile("full_adder.vcd");
	$dumpvars(0, t_full_adder);
end

initial #400 $finish;
endmodule

OLD_SLIDES/A1/4/full_adder.vcd
$date
	Mon Oct 15 15:08:46 2018
$end
$version
	Icarus Verilog
$end
$timescale
	1s
$end
$scope module t_full_adder $end
$var wire 1 ! S $end
$var wire 1 " Cout $end
$var reg 1 # A $end
$var reg 1 $ B $end
$var reg 1 % Cin $end
$scope module FA $end
$var wire 1 # A $end
$var wire 1 $ B $end
$var wire 1 % Cin $end
$var wire 1 " Cout $end
$var wire 1 & S1 $end
$var wire 1 ! S $end
$var wire 1 ' C2 $end
$var wire 1 ( C1 $end
$scope module HA1 $end
$var wire 1 # A $end
$var wire 1 $ B $end
$var wire 1 ( C $end
$var wire 1 & S $end
$upscope $end
$scope module HA2 $end
$var wire 1 & A $end
$var wire 1 % B $end
$var wire 1 ' C $end
$var wire 1 ! S $end
$upscope $end
$upscope $end
$upscope $end
$enddefinitions $end
#0
$dumpvars
0(
0'
0&
0%
0$
0#
0"
0!
$end
#50
1!
1%
#100
1&
1!
1$
0%
#150
1"
1'
0!
1%
#200
0"
0'
1!
1#
0$
0%
#250
1"
1'
0!
1%
#300
1(
0&
0'
0!
1$
0%
#350
1!
1%
