OLD_SLIDES/A2-final/1/mux_4X1.v
/***************************************************
* 4X1 MUX program
* Shanthanu S Rai(17CO242) and Varun Pattar(17CO249)
* October 13, 2018
****************************************************/

module mux_4X1(
input[N-1:0] in,
input[N/2-1:0] select,
output out
);

parameter N = 4;

wire[N-1:0] in;
wire[N/2-1:0] select;
wire out;

assign out = in[select];

endmodule

OLD_SLIDES/A1/3/half_adder.v
/*************************************************
* Half Adder program
* Shanthanu S Rai(17CO242) and Varun Pattar(17CO249)
* October 13, 2018
*************************************************/

module half_adder(A,B,C,S);

input A,B;
output C,S;

and G1(C,A,B);
xor G2(S,A,B);

endmodule

OLD_SLIDES/A2-final/2/full_adder.v
/*************************************************
* Full Adder program
* Shanthanu S Rai(17CO242) and Varun Pattar(17CO249)
* October 13, 2018
*************************************************/

`include "half_adder.v"

module full_adder(A,B,Cin,Cout,S);

input A,B,Cin;
output Cout, S;
wire S1,C1,C2;

half_adder HA1(A,B,C1,S1);
half_adder HA2(S1,Cin,C2,S);
or G(Cout,C1,C2);

endmodule

OLD_SLIDES/A2-final/4/mux_2X1.v
/***************************************************
* 2X1 MUX program
* Shanthanu S Rai(17CO242) and Varun Pattar(17CO249)
* October 13, 2018
****************************************************/

module mux_2X1(
input[N-1:0] in,
input[N/2-1:0] select,
output out
);

parameter N = 2;

wire[N-1:0] in;
wire[N/2-1:0] select;
wire out;

assign out = in[select];

endmodule

OLD_SLIDES/A2-final/2/ALU.v
/*****************************************************
* 1 bit ALU
* Shanthanu S Rai(17CO242) and Varun Pattar(17CO249)
* October 21, 2018
******************************************************/

`include "full_adder.v"
`include "mux_2X1.v"
`include "mux_4X1.v"

module ALU(
input Ainvert, Binvert, Cin,
input[1:0] Op,
input a, b,
output result, Cout, zero
);

reg zero;
wire oa, ob, result;

wire[1:0] in_a, in_b;
assign in_a[0] = a;
assign in_a[1] = ~a;
assign in_b[0] = b;
assign in_b[1] = ~b;

mux_2X1 m1(in_a, Ainvert, oa);
mux_2X1 m2(in_b, Binvert, ob);

wire[3:0] out;

and A(out[0],oa,ob);
or O(out[1],oa,ob);
full_adder S(oa,ob,Cin,Cout,out[2]);

mux_4X1 m3(out, Op, result);

always @ (Op, Cin, a, b, Ainvert, Binvert) begin
	if(result == 0)
		assign zero = 1;
	else
		assign zero = 0;
end

endmodule

OLD_SLIDES/A2-final/1/t_ALU.v
/*****************************************************
* Test bench for 1 bit ALU
* Shanthanu S Rai(17CO242) and Varun Pattar(17CO249)
* October 22, 2018
******************************************************/

`include "ALU.v"

module t_ALU;
	
	reg Ainvert, Binvert, Cin;
	reg[1:0] Op;
	reg a,b;
	wire result, Cout, zero;

	ALU alu(Ainvert, Binvert, Cin, Op, a, b, result, Cout, zero);

	initial begin
		$monitor($time," Ainvert=%b, Binvert=%b, Cin=%b, Op=%b, a=%b, b=%b, result=%b, Cout=%b, zero=%b",Ainvert,Binvert,Cin,Op,a,b,result,Cout,zero);
		#10
		{Ainvert, Binvert, Cin} = 3'bxxx;
		Op = 2'bxx;
		#10 
		{Ainvert, Binvert, Cin} = 3'b000;
		Op = 2'b00;
		    {a, b} = 2'b00;
		#10 {a, b} = 2'b01;
		#10 {a, b} = 2'b10;
		#10 {a, b} = 2'b11;
		#10
		{Ainvert, Binvert, Cin} = 3'b000;
		Op = 2'b01;
		    {a, b} = 2'b00;
		#10 {a, b} = 2'b01;
		#10 {a, b} = 2'b10;
		#10 {a, b} = 2'b11;
		#10
		{Ainvert, Binvert, Cin} = 3'b11x;
		Op = 2'b01;
		    {a, b} = 2'b00;
		#10 {a, b} = 2'b01;
		#10 {a, b} = 2'b10;
		#10 {a, b} = 2'b11;
		#10
		{Ainvert, Binvert, Cin} = 3'b11x;
		Op = 2'b00;
		    {a, b} = 2'b00;
		#10 {a, b} = 2'b01;
		#10 {a, b} = 2'b10;
		#10 {a, b} = 2'b11;
		#10
		{Ainvert, Binvert, Cin} = 3'b000;
		Op = 2'b10;
		    {a, b} = 2'b00;
		#10 {a, b} = 2'b01;
		#10 {a, b} = 2'b10;
		#10 {a, b} = 2'b11;
		#10
		{Ainvert, Binvert, Cin} = 3'b011;
		Op = 2'b10;
		    {a, b} = 2'b00;
		#10 {a, b} = 2'b01;
		#10 {a, b} = 2'b10;
		#10 {a, b} = 2'b11;
	end

	initial begin	
		$dumpfile("t_ALU.vcd");
		$dumpvars(0, t_ALU);
	end
	
	initial #260 $finish;

endmodule

OLD_SLIDES/A2-final/1/t_ALU.vcd
$date
	Tue Oct 23 11:54:27 2018
$end
$version
	Icarus Verilog
$end
$timescale
	1s
$end
$scope module t_ALU $end
$var wire 1 ! zero $end
$var wire 1 " result $end
$var wire 1 # Cout $end
$var reg 1 $ Ainvert $end
$var reg 1 % Binvert $end
$var reg 1 & Cin $end
$var reg 2 ' Op [1:0] $end
$var reg 1 ( a $end
$var reg 1 ) b $end
$scope module alu $end
$var wire 1 $ Ainvert $end
$var wire 1 % Binvert $end
$var wire 1 & Cin $end
$var wire 2 * Op [1:0] $end
$var wire 1 ( a $end
$var wire 1 ) b $end
$var wire 1 " result $end
$var wire 4 + out [3:0] $end
$var wire 1 , ob $end
$var wire 1 - oa $end
$var wire 2 . in_b [1:0] $end
$var wire 2 / in_a [1:0] $end
$var wire 1 # Cout $end
$var reg 1 ! zero $end
$scope module S $end
$var wire 1 & Cin $end
$var wire 1 # Cout $end
$var wire 1 0 S1 $end
$var wire 1 1 S $end
$var wire 1 2 C2 $end
$var wire 1 3 C1 $end
$var wire 1 , B $end
$var wire 1 - A $end
$scope module HA1 $end
$var wire 1 3 C $end
$var wire 1 0 S $end
$var wire 1 , B $end
$var wire 1 - A $end
$upscope $end
$scope module HA2 $end
$var wire 1 0 A $end
$var wire 1 & B $end
$var wire 1 2 C $end
$var wire 1 1 S $end
$upscope $end
$upscope $end
$scope module m1 $end
$var wire 2 4 in [1:0] $end
$var wire 1 $ select $end
$var wire 1 - out $end
$upscope $end
$scope module m2 $end
$var wire 2 5 in [1:0] $end
$var wire 1 % select $end
$var wire 1 , out $end
$upscope $end
$scope module m3 $end
$var wire 4 6 in [3:0] $end
$var wire 2 7 select [1:0] $end
$var wire 1 " out $end
$upscope $end
$upscope $end
$upscope $end
$enddefinitions $end
#0
$dumpvars
bx 7
bzxxx 6
bx 5
bx 4
x3
x2
x1
x0
bx /
bx .
x-
x,
bzxxx +
bx *
x)
x(
bx '
x&
x%
x$
x#
x"
x!
$end
#20
01
0#
00
03
0"
bz000 +
bz000 6
02
0!
0-
b10 /
b10 4
0(
0,
b10 .
b10 5
0)
b0 '
b0 *
b0 7
0$
0%
0&
#30
11
10
bz110 +
bz110 6
1!
1,
b1 .
b1 5
1)
#40
1-
b1 /
b1 4
1(
0,
b10 .
b10 5
0)
#50
01
1#
00
13
1"
bz011 +
bz011 6
1,
b1 .
b1 5
1)
#60
0#
03
0"
bz000 +
bz000 6
0!
0-
b10 /
b10 4
0(
0,
b10 .
b10 5
0)
b1 '
b1 *
b1 7
#70
11
10
1"
bz110 +
bz110 6
1!
1,
b1 .
b1 5
1)
#80
0!
1-
b1 /
b1 4
1(
0,
b10 .
b10 5
0)
#90
01
1#
00
13
bz011 +
bz011 6
1,
b1 .
b1 5
1)
#100
1#
13
1"
bzx11 +
bzx11 6
x1
b10 /
b10 4
0(
b10 .
b10 5
0)
1-
1$
1,
1%
x&
#110
x2
x#
10
03
bzx10 +
bzx10 6
0,
b1 .
b1 5
1)
#120
0-
1,
b1 /
b1 4
1(
b10 .
b10 5
0)
#130
0#
02
00
0"
bzx00 +
bzx00 6
0,
b1 .
b1 5
1)
#140
1#
13
1"
bzx11 +
bzx11 6
1-
1,
1!
b10 /
b10 4
0(
b10 .
b10 5
0)
b0 '
b0 *
b0 7
#150
x2
x#
10
03
0"
bzx10 +
bzx10 6
0,
0!
b1 .
b1 5
1)
#160
0-
1,
1!
b1 /
b1 4
1(
b10 .
b10 5
0)
#170
0#
02
00
bzx00 +
bzx00 6
0,
b1 .
b1 5
1)
#180
bz000 +
bz000 6
01
0!
b10 /
b10 4
0(
b10 .
b10 5
0)
0"
b10 '
b10 *
b10 7
0-
0$
0,
0%
0&
#190
1"
11
10
bz110 +
bz110 6
1!
1,
b1 .
b1 5
1)
#200
0!
1-
b1 /
b1 4
1(
0,
b10 .
b10 5
0)
#210
0"
01
1#
00
13
bz011 +
bz011 6
1,
b1 .
b1 5
1)
#220
12
10
1#
03
0"
bz010 +
bz010 6
01
1!
0-
b10 /
b10 4
0(
b10 .
b10 5
0)
1,
1%
1&
#230
0#
02
1"
11
00
bz100 +
bz100 6
0,
b1 .
b1 5
1)
#240
1#
13
bz111 +
bz111 6
1,
0!
1-
b1 /
b1 4
1(
b10 .
b10 5
0)
#250
12
0"
01
1#
10
03
bz010 +
bz010 6
0,
b1 .
b1 5
1)
