A1/InstructionFetch/IF.v
//Ankit Jain (17CO208) and Abhinav PY (17CO103)
module instructionFetch(clk,reset,instruction);
reg[31:0] IM[0:7];
input clk,reset;
output reg[31:0] instruction;
reg[2:0] pc;


initial
begin
	pc<=0;
	IM[0]=32'haffa01aa;
	IM[1]=32'habcdef12;
	IM[2]=32'h09128745;
	IM[3]=32'h1839405f;
	IM[4]=32'habcef264;
	IM[5]=32'h3682bcef;
	IM[6]=32'h18364789;
	IM[7]=32'hafccaaaa;
end

always@(posedge reset)
begin
	
	pc<=3'b0;
end

always@(posedge clk)
begin
	//$display("after posedge");
	instruction<=IM[pc];
	pc=pc+1;
end

endmodule

A1/InstructionFetch/IF_tb.v
//Ankit Jain (17CO208) and Abhinav PY (17CO103)
`include "IF.v"
module IF_tb;
reg clk,reset;
wire[31:0] instruction;
instructionFetch A(clk,reset,instruction);

initial 
begin
	clk=1'b0;
	reset=0;
	#1 reset=1;
	#1 reset=0;
	repeat(16)
		#5 clk = ~clk;
end

initial
begin
	$dumpfile("IF_tb.vcd");
	$dumpvars(0,IF_tb);
	$display("instruction");
	
	//$monitor("%32b %d",instruction,clk);
end

always@(negedge clk)
begin
	$display("%32b\n",instruction);
end

endmodule

A1/InstructionFetch/IF_tb.vcd
$date
	Sat Jan  5 11:18:12 2019
$end
$version
	Icarus Verilog
$end
$timescale
	1s
$end
$scope module IF_tb $end
$var wire 32 ! instruction [31:0] $end
$var reg 1 " clk $end
$var reg 1 # reset $end
$scope module A $end
$var wire 1 " clk $end
$var wire 1 # reset $end
$var reg 32 $ instruction [31:0] $end
$var reg 3 % pc [2:0] $end
$upscope $end
$upscope $end
$enddefinitions $end
#0
$dumpvars
b0 %
bx $
0#
0"
bx !
$end
#1
1#
#2
0#
#7
b10101111111110100000000110101010 !
b10101111111110100000000110101010 $
b1 %
1"
#12
0"
#17
b10101011110011011110111100010010 !
b10101011110011011110111100010010 $
b10 %
1"
#22
0"
#27
b1001000100101000011101000101 !
b1001000100101000011101000101 $
b11 %
1"
#32
0"
#37
b11000001110010100000001011111 !
b11000001110010100000001011111 $
b100 %
1"
#42
0"
#47
b10101011110011101111001001100100 !
b10101011110011101111001001100100 $
b101 %
1"
#52
0"
#57
b110110100000101011110011101111 !
b110110100000101011110011101111 $
b110 %
1"
#62
0"
#67
b11000001101100100011110001001 !
b11000001101100100011110001001 $
b111 %
1"
#72
0"
#77
b10101111110011001010101010101010 !
b10101111110011001010101010101010 $
b0 %
1"
