OLD_SLIDES/A1/1/module1.v
/*************************************************
* Hello World program
* Shanthanu S Rai(17CO242) and Varun Pattar(17CO249)
* October 13, 2018
*************************************************/

module t_hello_world;
 
integer i;

initial begin
 for(i = 1; i <= 100; i = i+1) begin
  #1 $display ($time, " Hello World");
 end
end

initial begin  
 $dumpfile("module1.vcd");
 $dumpvars(0, t_hello_world);
end

endmodule

OLD_SLIDES/A1/1/module1.vcd
$date
	Sat Oct 13 10:49:33 2018
$end
$version
	Icarus Verilog
$end
$timescale
	1s
$end
$scope module t_hello_world $end
$var integer 32 ! i [31:0] $end
$upscope $end
$enddefinitions $end
#0
$dumpvars
b1 !
$end
#1
b10 !
#2
b11 !
#3
b100 !
#4
b101 !
#5
b110 !
#6
b111 !
#7
b1000 !
#8
b1001 !
#9
b1010 !
#10
b1011 !
#11
b1100 !
#12
b1101 !
#13
b1110 !
#14
b1111 !
#15
b10000 !
#16
b10001 !
#17
b10010 !
#18
b10011 !
#19
b10100 !
#20
b10101 !
#21
b10110 !
#22
b10111 !
#23
b11000 !
#24
b11001 !
#25
b11010 !
#26
b11011 !
#27
b11100 !
#28
b11101 !
#29
b11110 !
#30
b11111 !
#31
b100000 !
#32
b100001 !
#33
b100010 !
#34
b100011 !
#35
b100100 !
#36
b100101 !
#37
b100110 !
#38
b100111 !
#39
b101000 !
#40
b101001 !
#41
b101010 !
#42
b101011 !
#43
b101100 !
#44
b101101 !
#45
b101110 !
#46
b101111 !
#47
b110000 !
#48
b110001 !
#49
b110010 !
#50
b110011 !
#51
b110100 !
#52
b110101 !
#53
b110110 !
#54
b110111 !
#55
b111000 !
#56
b111001 !
#57
b111010 !
#58
b111011 !
#59
b111100 !
#60
b111101 !
#61
b111110 !
#62
b111111 !
#63
b1000000 !
#64
b1000001 !
#65
b1000010 !
#66
b1000011 !
#67
b1000100 !
#68
b1000101 !
#69
b1000110 !
#70
b1000111 !
#71
b1001000 !
#72
b1001001 !
#73
b1001010 !
#74
b1001011 !
#75
b1001100 !
#76
b1001101 !
#77
b1001110 !
#78
b1001111 !
#79
b1010000 !
#80
b1010001 !
#81
b1010010 !
#82
b1010011 !
#83
b1010100 !
#84
b1010101 !
#85
b1010110 !
#86
b1010111 !
#87
b1011000 !
#88
b1011001 !
#89
b1011010 !
#90
b1011011 !
#91
b1011100 !
#92
b1011101 !
#93
b1011110 !
#94
b1011111 !
#95
b1100000 !
#96
b1100001 !
#97
b1100010 !
#98
b1100011 !
#99
b1100100 !
#100
b1100101 !
