OLD_SLIDES/A1/2/decoder.v
/*************************************************
* 4X16 decoder
* Shanthanu S Rai(17CO242) and Varun Pattar(17CO249)
* October 13, 2018
*************************************************/

//design for 4X16 decoder
module decoder(in,out,enable);

input[3:0] in;
output[15:0] out;
input enable;
reg[15:0] out;

always @ (in or enable)
begin
	out = 16'h0000;
	if(enable) begin
		case(in)
			4'h0: out = 16'h0001;
			4'h1: out = 16'h0002;
			4'h2: out = 16'h0004;
			4'h3: out = 16'h0008;
			4'h4: out = 16'h0010;
			4'h5: out = 16'h0020;
			4'h6: out = 16'h0040;
			4'h7: out = 16'h0080;
			4'h8: out = 16'h0100;
			4'h9: out = 16'h0200;
			4'hA: out = 16'h0400;
			4'hB: out = 16'h0800;
			4'hC: out = 16'h1000;
			4'hD: out = 16'h2000;
			4'hE: out = 16'h4000;
			4'hF: out = 16'h8000;
		endcase
	end
end

endmodule

//test bench
module t_decoder;

reg[3:0] in;
reg enable;
wire[15:0] out;

decoder D(in, out, enable);

initial begin
	$monitor($time," enable = %b, in = %b, out = %b", enable, in, out);
	enable = 0;
#50	in = 	4'h0;
#50	in = 	4'h1;
#50  	in =	4'h2;
#50	in = 	4'h3;
#50	in = 	4'h4;
#50	in =	4'h5;
#50	in =	4'h6;
#50	in =	4'h7;
#50	in =	4'h8;
#50	in =	4'h9;
#50	in =	4'hA;
#50	in =	4'hB;
#50	in =	4'hC;
#50	in =	4'hD;
#50	in =	4'hE;
#50	in =	4'hF;
#50	enable = 1;
#50	in = 	4'h0;
#50	in = 	4'h1;
#50  	in =	4'h2;
#50	in = 	4'h3;
#50	in = 	4'h4;
#50	in =	4'h5;
#50	in =	4'h6;
#50	in =	4'h7;
#50	in =	4'h8;
#50	in =	4'h9;
#50	in =	4'hA;
#50	in =	4'hB;
#50	in =	4'hC;
#50	in =	4'hD;
#50	in =	4'hE;
#50 	in = 	4'hF;
end

initial begin
	$dumpfile("decoder.vcd");
	$dumpvars(0, t_decoder);
end

initial #2000 $finish;

endmodule

OLD_SLIDES/A1/2/decoder.vcd
$date
	Mon Oct 15 15:00:02 2018
$end
$version
	Icarus Verilog
$end
$timescale
	1s
$end
$scope module t_decoder $end
$var wire 16 ! out [15:0] $end
$var reg 1 " enable $end
$var reg 4 # in [3:0] $end
$scope module D $end
$var wire 1 " enable $end
$var wire 4 $ in [3:0] $end
$var reg 16 % out [15:0] $end
$upscope $end
$upscope $end
$enddefinitions $end
#0
$dumpvars
b0 %
bx $
bx #
0"
b0 !
$end
#50
b0 #
b0 $
#100
b1 #
b1 $
#150
b10 #
b10 $
#200
b11 #
b11 $
#250
b100 #
b100 $
#300
b101 #
b101 $
#350
b110 #
b110 $
#400
b111 #
b111 $
#450
b1000 #
b1000 $
#500
b1001 #
b1001 $
#550
b1010 #
b1010 $
#600
b1011 #
b1011 $
#650
b1100 #
b1100 $
#700
b1101 #
b1101 $
#750
b1110 #
b1110 $
#800
b1111 #
b1111 $
#850
b1000000000000000 !
b1000000000000000 %
1"
#900
b1 !
b1 %
b0 #
b0 $
#950
b10 !
b10 %
b1 #
b1 $
#1000
b100 !
b100 %
b10 #
b10 $
#1050
b1000 !
b1000 %
b11 #
b11 $
#1100
b10000 !
b10000 %
b100 #
b100 $
#1150
b100000 !
b100000 %
b101 #
b101 $
#1200
b1000000 !
b1000000 %
b110 #
b110 $
#1250
b10000000 !
b10000000 %
b111 #
b111 $
#1300
b100000000 !
b100000000 %
b1000 #
b1000 $
#1350
b1000000000 !
b1000000000 %
b1001 #
b1001 $
#1400
b10000000000 !
b10000000000 %
b1010 #
b1010 $
#1450
b100000000000 !
b100000000000 %
b1011 #
b1011 $
#1500
b1000000000000 !
b1000000000000 %
b1100 #
b1100 $
#1550
b10000000000000 !
b10000000000000 %
b1101 #
b1101 $
#1600
b100000000000000 !
b100000000000000 %
b1110 #
b1110 $
#1650
b1000000000000000 !
b1000000000000000 %
b1111 #
b1111 $
