OLD_SLIDES/A1/7/DFF.v
/*************************************************
* Behavioral code for D Flip Flop(with reset)
* Shanthanu S Rai(17CO242) and Varun Pattar(17CO249)
* October 14, 2018
*************************************************/

module D_FF(D,clk,Q,reset);

input D,clk,reset;
output Q;

reg Q;

always @ (posedge clk,negedge reset) begin
	if(reset == 0)
		Q <= 1'b0;
	else
		Q <= D;
end

endmodule

OLD_SLIDES/A1/7/reg.v
/*************************************************
* Register
* Shanthanu S Rai(17CO242) and Varun Pattar(17CO249)
* October 14, 2018
*************************************************/

`include "DFF.v"

module register(I,clk,O,reset);

parameter N = 32;
input[N-1:0] I;
input clk,reset;
output[N-1:0] O;

genvar i;
generate
	for(i = 0; i < N; i=i+1) begin
		D_FF d(I[i],clk,O[i],reset);		
	end	
endgenerate

endmodule

OLD_SLIDES/A1/7/t_reg.v
/*************************************************
* Test bench for Register
* Shanthanu S Rai(17CO242) and Varun Pattar(17CO249)
* October 14, 2018
*************************************************/

`include "reg.v"

module t_reg;

parameter N = 32;
reg[N-1:0] I;
reg clk = 1'b0,reset = 1'b0;
wire[N-1:0] O;

register R(I,clk,O,reset);

always #5 clk = ~clk;

initial begin
	$monitor($time," reset = %b, I = %d, clk = %b, O = %d", reset, I, clk, O);
	I = 21512;
#7	reset = 1'b1;
#7	I = 2352521;
#7	I = 3251255;
#7	I = 2254;
#7	I = 234522;
#7	I = 3425692;
#7	reset = 0;
#7	I = 13964;
#7	I = 342981;
#7	reset = 1;
#7	I = 4519856;
#7	I = 1;
end

initial begin
	$dumpfile("t_reg.vcd");
	$dumpvars(0, t_reg);
end

initial #100 $finish;

endmodule

OLD_SLIDES/A1/7/t_reg.vcd
$date
	Mon Oct 15 15:47:30 2018
$end
$version
	Icarus Verilog
$end
$timescale
	1s
$end
$scope module t_reg $end
$var wire 32 ! O [31:0] $end
$var reg 32 " I [31:0] $end
$var reg 1 # clk $end
$var reg 1 $ reset $end
$scope module R $end
$var wire 32 % I [31:0] $end
$var wire 1 # clk $end
$var wire 1 $ reset $end
$var wire 32 & O [31:0] $end
$scope begin genblk1[0] $end
$scope module d $end
$var wire 1 ' D $end
$var wire 1 # clk $end
$var wire 1 $ reset $end
$var reg 1 ( Q $end
$upscope $end
$upscope $end
$scope begin genblk1[1] $end
$scope module d $end
$var wire 1 ) D $end
$var wire 1 # clk $end
$var wire 1 $ reset $end
$var reg 1 * Q $end
$upscope $end
$upscope $end
$scope begin genblk1[2] $end
$scope module d $end
$var wire 1 + D $end
$var wire 1 # clk $end
$var wire 1 $ reset $end
$var reg 1 , Q $end
$upscope $end
$upscope $end
$scope begin genblk1[3] $end
$scope module d $end
$var wire 1 - D $end
$var wire 1 # clk $end
$var wire 1 $ reset $end
$var reg 1 . Q $end
$upscope $end
$upscope $end
$scope begin genblk1[4] $end
$scope module d $end
$var wire 1 / D $end
$var wire 1 # clk $end
$var wire 1 $ reset $end
$var reg 1 0 Q $end
$upscope $end
$upscope $end
$scope begin genblk1[5] $end
$scope module d $end
$var wire 1 1 D $end
$var wire 1 # clk $end
$var wire 1 $ reset $end
$var reg 1 2 Q $end
$upscope $end
$upscope $end
$scope begin genblk1[6] $end
$scope module d $end
$var wire 1 3 D $end
$var wire 1 # clk $end
$var wire 1 $ reset $end
$var reg 1 4 Q $end
$upscope $end
$upscope $end
$scope begin genblk1[7] $end
$scope module d $end
$var wire 1 5 D $end
$var wire 1 # clk $end
$var wire 1 $ reset $end
$var reg 1 6 Q $end
$upscope $end
$upscope $end
$scope begin genblk1[8] $end
$scope module d $end
$var wire 1 7 D $end
$var wire 1 # clk $end
$var wire 1 $ reset $end
$var reg 1 8 Q $end
$upscope $end
$upscope $end
$scope begin genblk1[9] $end
$scope module d $end
$var wire 1 9 D $end
$var wire 1 # clk $end
$var wire 1 $ reset $end
$var reg 1 : Q $end
$upscope $end
$upscope $end
$scope begin genblk1[10] $end
$scope module d $end
$var wire 1 ; D $end
$var wire 1 # clk $end
$var wire 1 $ reset $end
$var reg 1 < Q $end
$upscope $end
$upscope $end
$scope begin genblk1[11] $end
$scope module d $end
$var wire 1 = D $end
$var wire 1 # clk $end
$var wire 1 $ reset $end
$var reg 1 > Q $end
$upscope $end
$upscope $end
$scope begin genblk1[12] $end
$scope module d $end
$var wire 1 ? D $end
$var wire 1 # clk $end
$var wire 1 $ reset $end
$var reg 1 @ Q $end
$upscope $end
$upscope $end
$scope begin genblk1[13] $end
$scope module d $end
$var wire 1 A D $end
$var wire 1 # clk $end
$var wire 1 $ reset $end
$var reg 1 B Q $end
$upscope $end
$upscope $end
$scope begin genblk1[14] $end
$scope module d $end
$var wire 1 C D $end
$var wire 1 # clk $end
$var wire 1 $ reset $end
$var reg 1 D Q $end
$upscope $end
$upscope $end
$scope begin genblk1[15] $end
$scope module d $end
$var wire 1 E D $end
$var wire 1 # clk $end
$var wire 1 $ reset $end
$var reg 1 F Q $end
$upscope $end
$upscope $end
$scope begin genblk1[16] $end
$scope module d $end
$var wire 1 G D $end
$var wire 1 # clk $end
$var wire 1 $ reset $end
$var reg 1 H Q $end
$upscope $end
$upscope $end
$scope begin genblk1[17] $end
$scope module d $end
$var wire 1 I D $end
$var wire 1 # clk $end
$var wire 1 $ reset $end
$var reg 1 J Q $end
$upscope $end
$upscope $end
$scope begin genblk1[18] $end
$scope module d $end
$var wire 1 K D $end
$var wire 1 # clk $end
$var wire 1 $ reset $end
$var reg 1 L Q $end
$upscope $end
$upscope $end
$scope begin genblk1[19] $end
$scope module d $end
$var wire 1 M D $end
$var wire 1 # clk $end
$var wire 1 $ reset $end
$var reg 1 N Q $end
$upscope $end
$upscope $end
$scope begin genblk1[20] $end
$scope module d $end
$var wire 1 O D $end
$var wire 1 # clk $end
$var wire 1 $ reset $end
$var reg 1 P Q $end
$upscope $end
$upscope $end
$scope begin genblk1[21] $end
$scope module d $end
$var wire 1 Q D $end
$var wire 1 # clk $end
$var wire 1 $ reset $end
$var reg 1 R Q $end
$upscope $end
$upscope $end
$scope begin genblk1[22] $end
$scope module d $end
$var wire 1 S D $end
$var wire 1 # clk $end
$var wire 1 $ reset $end
$var reg 1 T Q $end
$upscope $end
$upscope $end
$scope begin genblk1[23] $end
$scope module d $end
$var wire 1 U D $end
$var wire 1 # clk $end
$var wire 1 $ reset $end
$var reg 1 V Q $end
$upscope $end
$upscope $end
$scope begin genblk1[24] $end
$scope module d $end
$var wire 1 W D $end
$var wire 1 # clk $end
$var wire 1 $ reset $end
$var reg 1 X Q $end
$upscope $end
$upscope $end
$scope begin genblk1[25] $end
$scope module d $end
$var wire 1 Y D $end
$var wire 1 # clk $end
$var wire 1 $ reset $end
$var reg 1 Z Q $end
$upscope $end
$upscope $end
$scope begin genblk1[26] $end
$scope module d $end
$var wire 1 [ D $end
$var wire 1 # clk $end
$var wire 1 $ reset $end
$var reg 1 \ Q $end
$upscope $end
$upscope $end
$scope begin genblk1[27] $end
$scope module d $end
$var wire 1 ] D $end
$var wire 1 # clk $end
$var wire 1 $ reset $end
$var reg 1 ^ Q $end
$upscope $end
$upscope $end
$scope begin genblk1[28] $end
$scope module d $end
$var wire 1 _ D $end
$var wire 1 # clk $end
$var wire 1 $ reset $end
$var reg 1 ` Q $end
$upscope $end
$upscope $end
$scope begin genblk1[29] $end
$scope module d $end
$var wire 1 a D $end
$var wire 1 # clk $end
$var wire 1 $ reset $end
$var reg 1 b Q $end
$upscope $end
$upscope $end
$scope begin genblk1[30] $end
$scope module d $end
$var wire 1 c D $end
$var wire 1 # clk $end
$var wire 1 $ reset $end
$var reg 1 d Q $end
$upscope $end
$upscope $end
$scope begin genblk1[31] $end
$scope module d $end
$var wire 1 e D $end
$var wire 1 # clk $end
$var wire 1 $ reset $end
$var reg 1 f Q $end
$upscope $end
$upscope $end
$upscope $end
$upscope $end
$enddefinitions $end
#0
$dumpvars
0f
0e
0d
0c
0b
0a
0`
0_
0^
0]
0\
0[
0Z
0Y
0X
0W
0V
0U
0T
0S
0R
0Q
0P
0O
0N
0M
0L
0K
0J
0I
0H
0G
0F
0E
0D
1C
0B
0A
0@
1?
0>
0=
0<
1;
0:
09
08
07
06
05
04
03
02
01
00
0/
0.
1-
0,
0+
0*
0)
0(
0'
b0 &
b101010000001000 %
0$
0#
b101010000001000 "
b0 !
$end
#5
1#
#7
1$
#10
0#
#14
1'
15
17
0?
1A
1E
1G
1I
1Q
b1000111110010110001001 "
b1000111110010110001001 %
#15
1(
1.
16
18
1<
1B
1D
1F
1H
1J
b1000111110010110001001 !
b1000111110010110001001 &
1R
1#
#20
0#
#21
1)
1+
0-
1/
11
05
07
1=
1?
0A
0C
0I
1O
b1100011001110000110111 "
b1100011001110000110111 %
#25
1P
0J
0D
0B
1@
1>
08
06
12
10
0.
1,
b1100011001110000110111 !
b1100011001110000110111 &
1*
1#
#28
0'
1-
0/
01
13
15
0;
0?
0E
0G
0O
0Q
b100011001110 "
b100011001110 %
#30
0#
#35
0(
0,
1.
02
0>
1J
0P
b111001010000011010 !
b111001010000011010 &
0R
0+
1/
03
05
1;
0=
1?
1E
1G
1I
1#
b111001010000011010 "
b111001010000011010 %
#40
0#
#42
0)
1+
15
17
0?
1C
0E
0G
0I
1K
1O
1Q
b1101000100010110011100 "
b1101000100010110011100 %
#45
1R
1P
1L
0J
0H
0F
1D
0@
18
16
1,
b1101000100010110011100 !
b1101000100010110011100 &
0*
1#
#49
0,
0.
00
06
08
0<
0D
0L
0P
b0 !
b0 &
0R
0$
#50
0#
#55
1#
#56
0/
07
19
1?
1A
0C
0K
0O
0Q
b11011010001100 "
b11011010001100 %
#60
0#
#63
1'
0-
13
17
0;
1=
1G
1K
b1010011101111000101 "
b1010011101111000101 %
#65
1#
#70
0#
1$
#75
1L
1H
1B
1@
1>
1:
18
16
14
1,
b1010011101111000101 !
b1010011101111000101 &
1(
1#
#77
0'
0+
1/
11
03
1;
0=
1C
1E
0G
1S
b10001001111011110110000 "
b10001001111011110110000 %
#80
0#
#84
1'
0/
01
05
07
09
0;
0?
0A
0C
0E
0K
0S
b1 "
b1 %
#85
0,
04
06
08
0:
0>
0@
0B
0H
b1 !
b1 &
0L
1#
