A2/4-BranchOnEqualInstructionDatapath/ALUcontrol.v
/*****************************************************
* ALU Control
* Shanthanu S Rai(17CO242) and Varun Pattar(17CO249)
* October 23, 2018
******************************************************/

module ALUcontrol(
input ALUOp1, ALUOp0,
input[6:0] funct7,
input[2:0] funct3,
output[3:0] Op
);

reg[3:0] Op;
wire f;

assign f = funct7[5];

always @ (ALUOp1, ALUOp0, f, funct3) begin
	
	if(ALUOp1 == 1'b0 && ALUOp0 == 1'b0)
		Op = 4'b0010;
	else if(ALUOp1 == 1'b0 && ALUOp0 == 1'b1)
		Op = 4'b0110;
	else if(ALUOp1 == 1'b1 && ALUOp0 == 1'b0) begin
		if(f == 1'b0 && funct3 == 3'b000)
			Op = 4'b0010;
		else if(f == 1'b1 && funct3 == 3'b000)
			Op = 4'b0110;
		else if(f == 1'b0 && funct3 == 3'b111)
			Op = 4'b0000;
		else if(f == 1'b0 && funct3 == 3'b110)
			Op = 4'b0001;
	end
	else 
		Op <= Op;
end

endmodule

OLD_SLIDES/A2-final/3/t_ALUcontrol.v
/*****************************************************
* Test bench for ALU Control
* Shanthanu S Rai(17CO242) and Varun Pattar(17CO249)
* October 23, 2018
******************************************************/

`include "ALUcontrol.v"

module t_ALUcontrol;

reg ALUOp1, ALUOp0;
reg[6:0] funct7;
reg[2:0] funct3;
wire[3:0] Op;

ALUcontrol A(ALUOp1, ALUOp0, funct7, funct3, Op);

initial begin
	
	$monitor($time, " ALUOp1 = %b, ALUOp0 = %b, funct7 = %b, funct3 = %b, Op = %b", ALUOp1, ALUOp0, funct7, funct3, Op);
	{ALUOp1, ALUOp0} = 2'b00;
	funct7 = 7'bxxxxxxx;
	funct3 = 3'bxxx;
	#10
	ALUOp0 = 1;
	#10
	ALUOp1 = 1;
	#10
	ALUOp0 = 0;
	funct7[5] = 0; 
	funct3 = 3'b000;
	#10
	funct7[5] = 1; 
	funct3 = 3'b000;
	#10
	funct7[5] = 0; 
	funct3 = 3'b111;
	#10
	funct7[5] = 0; 
	funct3 = 3'b110;
	#10
	ALUOp0 = 1;
end

initial begin
	$dumpfile("t_ALUcontrol.vcd");
	$dumpvars(0, t_ALUcontrol);
end 

initial #70 $finish;

endmodule

OLD_SLIDES/A2-final/3/t_ALUcontrol.vcd
$date
	Tue Oct 23 12:50:53 2018
$end
$version
	Icarus Verilog
$end
$timescale
	1s
$end
$scope module t_ALUcontrol $end
$var wire 4 ! Op [3:0] $end
$var reg 1 " ALUOp0 $end
$var reg 1 # ALUOp1 $end
$var reg 3 $ funct3 [2:0] $end
$var reg 7 % funct7 [6:0] $end
$scope module A $end
$var wire 1 " ALUOp0 $end
$var wire 1 # ALUOp1 $end
$var wire 3 & funct3 [2:0] $end
$var wire 7 ' funct7 [6:0] $end
$var wire 1 ( f $end
$var reg 4 ) Op [3:0] $end
$upscope $end
$upscope $end
$enddefinitions $end
#0
$dumpvars
b10 )
x(
bx '
bx &
bx %
bx $
0#
0"
b10 !
$end
#10
b110 !
b110 )
1"
#20
1#
#30
b10 !
b10 )
0(
b0 $
b0 &
bx0xxxxx %
bx0xxxxx '
0"
#40
b110 !
b110 )
1(
bx1xxxxx %
bx1xxxxx '
#50
b0 !
b0 )
0(
b111 $
b111 &
bx0xxxxx %
bx0xxxxx '
#60
b1 !
b1 )
b110 $
b110 &
#70
1"
