OLD_SLIDES/A1/6/DFF-v3.v
/*************************************************
* Behavioral code for D Flip Flop
* Shanthanu S Rai(17CO242) and Varun Pattar(17CO249)
* October 14, 2018
*************************************************/

module D_FF(D,clk,Q,Qbar);

input D,clk;
output Q,Qbar;

reg Q,Qbar;

always @ (posedge clk) begin
	Q <= D;
	Qbar <= ~D;
end

endmodule

OLD_SLIDES/A1/6/t_DFF.v
/*************************************************
* Test bench for testing D Flip flop(all 3)
* Shanthanu S Rai(17CO242) and Varun Pattar(17CO249)
* October 14, 2018
*************************************************/

//include different versions for testing differnet D FFs
`include "DFF-v3.v"

module t_DFF;

reg D, clk = 1'b0;
wire Q,Qbar;

D_FF d(D,clk,Q,Qbar);

//assign clk = 1'b1;
always #10 clk = ~clk;


initial begin
	
end

initial begin
	$monitor($time," D = %b, clk = %b, Q = %b, Qbar = %b", D, clk, Q, Qbar);
	D = 1'b1;
#20	D = 1'b0;
#30 	D = 1'b1;
#50 	D = 1'b0;
#40	D = 1'b1;
#20 	D = 1'b0;
#30 	D = 1'b1;
#10	D = 1'b0;
end

initial begin
	//change dumpfile to relevant version
	$dumpfile("t_DFF-v3.vcd");
	$dumpvars(0, t_DFF);
end

initial #200 $finish;

endmodule

OLD_SLIDES/A1/6/t_DFF-v3.vcd
$date
	Mon Oct 15 15:44:07 2018
$end
$version
	Icarus Verilog
$end
$timescale
	1s
$end
$scope module t_DFF $end
$var wire 1 ! Qbar $end
$var wire 1 " Q $end
$var reg 1 # D $end
$var reg 1 $ clk $end
$scope module d $end
$var wire 1 # D $end
$var wire 1 $ clk $end
$var reg 1 " Q $end
$var reg 1 ! Qbar $end
$upscope $end
$upscope $end
$enddefinitions $end
#0
$dumpvars
0$
1#
x"
x!
$end
#10
0!
1"
1$
#20
0$
0#
#30
1!
0"
1$
#40
0$
#50
0!
1"
1$
1#
#60
0$
#70
1$
#80
0$
#90
1$
#100
0$
0#
#110
1!
0"
1$
#120
0$
#130
1$
#140
0$
1#
#150
0!
1"
1$
#160
0$
0#
#170
1!
0"
1$
#180
0$
#190
0!
1"
1$
1#
#200
0$
0#
